ocher/__init__.py
ocher-0.1.0.dist-info/METADATA
ocher-0.1.0.dist-info/WHEEL
ocher-0.1.0.dist-info/top_level.txt
ocher-0.1.0.dist-info/RECORD
