Metadata-Version: 2.1
Name: ocher
Version: 0.1.0
Summary: Python client for Ocher queues
Home-page: https://github.com/mkuznets/ocher
Author: Max Kuznetsov
Author-email: maks.kuznetsov@gmail.com
License: MIT
Platform: any
Classifier: License :: OSI Approved :: MIT License
Classifier: Operating System :: OS Independent
Classifier: Programming Language :: Python :: 3 :: Only
Requires-Python: >=3.7
Requires-Dist: grpcio (>=1.28.1)
Provides-Extra: dev
Requires-Dist: grpcio-tools (>=1.28.1) ; extra == 'dev'
